qpSWIFT.cp311-win_amd64.pyd
EasyTeleop/Components/DataCollect.py
EasyTeleop/Components/HandVisualizer.py
EasyTeleop/Components/Interpolation.py
EasyTeleop/Components/PostProcess.py
EasyTeleop/Components/StreamTracker.py
EasyTeleop/Components/TeleopMiddleware.py
EasyTeleop/Components/VRPacketAnalyzer.py
EasyTeleop/Components/Visualizer.py
EasyTeleop/Components/WebRTC.py
EasyTeleop/Components/__init__.py
EasyTeleop/Components/convert_to_hdf5.py
EasyTeleop/Device/BaseDevice.py
EasyTeleop/Device/__init__.py
EasyTeleop/Device/Camera/BaseCamera.py
EasyTeleop/Device/Camera/RealSenseCamera.py
EasyTeleop/Device/Camera/TestCamera.py
EasyTeleop/Device/Camera/__init__.py
EasyTeleop/Device/Hand/BaseHand.py
EasyTeleop/Device/Hand/Revo2OnRealMan.py
EasyTeleop/Device/Hand/__init__.py
EasyTeleop/Device/Robot/BaseRobot.py
EasyTeleop/Device/Robot/RealMan.py
EasyTeleop/Device/Robot/RealManWithIK.py
EasyTeleop/Device/Robot/TestRobot.py
EasyTeleop/Device/Robot/__init__.py
EasyTeleop/Device/Robot/Realman_IK/__init__.py
EasyTeleop/Device/Robot/Realman_IK/ik_qp.py
EasyTeleop/Device/Robot/Realman_IK/ik_rbtdef.py
EasyTeleop/Device/Robot/Realman_IK/ik_rbtutils.py
EasyTeleop/Device/Robot/Realman_IK/rm_ik.py
EasyTeleop/Device/VR/BaseVR.py
EasyTeleop/Device/VR/TestVR.py
EasyTeleop/Device/VR/VRSocket.py
EasyTeleop/Device/VR/__init__.py
EasyTeleop/TeleopGroup/BaseTeleopGroup.py
EasyTeleop/TeleopGroup/SingleArmWithTriggerTeleopGroup.py
EasyTeleop/TeleopGroup/TwoArmWithTriggerTeleopGroup.py
EasyTeleop/TeleopGroup/__init__.py
easyteleop-0.2.5.dist-info/licenses/LICENSE
easyteleop-0.2.5.dist-info/METADATA
easyteleop-0.2.5.dist-info/WHEEL
easyteleop-0.2.5.dist-info/top_level.txt
easyteleop-0.2.5.dist-info/RECORD
