Metadata-Version: 2.4
Name: EasyTeleop
Version: 0.2.5
Summary: Easy teleoperate tools for robotic devices control with VR headset
Author-email: Chain Pray <qianpurui@gmail.com>
License-Expression: MIT
Classifier: Development Status :: 4 - Beta
Classifier: Intended Audience :: Developers
Classifier: Intended Audience :: Science/Research
Classifier: Topic :: Scientific/Engineering :: Artificial Intelligence
Classifier: Programming Language :: Python
Classifier: Programming Language :: Python :: 3
Classifier: Programming Language :: Python :: 3 :: Only
Classifier: Programming Language :: Python :: 3.10
Classifier: Programming Language :: Python :: 3.11
Classifier: Programming Language :: Python :: 3.12
Classifier: Operating System :: OS Independent
Requires-Python: >=3.10
License-File: LICENSE
Requires-Dist: aiortc>=1.13.0
Requires-Dist: av>=14.4.0
Requires-Dist: h5py>=3.15.1
Requires-Dist: matplotlib>=3.10.7
Requires-Dist: numpy>=2.2.6
Requires-Dist: opencv-python>=4.11.0.86
Requires-Dist: pyrealsense2>=2.56.5.9235
Requires-Dist: robotic-arm>=1.1.1
Requires-Dist: scipy>=1.15.3
Requires-Dist: websockets>=15.0.1
Dynamic: license-file
